{
  "data": {},
  "elements": {
    "nodes": [
      {
        "data": {
          "name": "AKT1",
          "label": "AKT1",
          "color": "#FFFFFF",
          "id": "AKT1"
        }
      },
      {
        "data": {
          "name": "ESR1",
          "label": "ESR1",
          "color": "#FFFFFF",
          "id": "ESR1"
        }
      },
      {
        "data": {
          "name": "MTOR",
          "label": "MTOR",
          "color": "#FFFFFF",
          "id": "MTOR"
        }
      },
      {
        "data": {
          "name": "BAD",
          "label": "BAD",
          "color": "#FFFFFF",
          "id": "BAD"
        }
      },
      {
        "data": {
          "name": "GSK3B",
          "label": "GSK3B",
          "color": "#FFFFFF",
          "id": "GSK3B"
        }
      },
      {
        "data": {
          "name": "MAPK1",
          "label": "MAPK1",
          "color": "#FFFFFF",
          "id": "MAPK1"
        }
      },
      {
        "data": {
          "name": "AKT1S1",
          "label": "AKT1S1",
          "color": "#FFFFFF",
          "id": "AKT1S1"
        }
      },
      {
        "data": {
          "name": "GSK3A",
          "label": "GSK3A",
          "color": "#FFFFFF",
          "id": "GSK3A"
        }
      }
    ],
    "edges": [
      {
        "data": {
          "source": "AKT1",
          "target": "ESR1",
          "interactionType": "phosphorylates",
          "color": "#00ff00",
          "lty": 1
        }
      },
      {
        "data": {
          "source": "ESR1",
          "target": "AKT1",
          "interactionType": "phosphorylates",
          "color": "#00ff00",
          "lty": 1
        }
      },
      {
        "data": {
          "source": "AKT1",
          "target": "MTOR",
          "interactionType": "phosphorylates",
          "color": "#00ff00",
          "lty": 1
        }
      },
      {
        "data": {
          "source": "MTOR",
          "target": "AKT1",
          "interactionType": "phosphorylates",
          "color": "#00ff00",
          "lty": 1
        }
      },
      {
        "data": {
          "source": "AKT1",
          "target": "BAD",
          "interactionType": "phosphorylates",
          "color": "#00ff00",
          "lty": 1
        }
      },
      {
        "data": {
          "source": "AKT1",
          "target": "GSK3B",
          "interactionType": "phosphorylates",
          "color": "#00ff00",
          "lty": 1
        }
      },
      {
        "data": {
          "source": "MAPK1",
          "target": "AKT1",
          "interactionType": "phosphorylates",
          "color": "#00ff00",
          "lty": 1
        }
      },
      {
        "data": {
          "source": "MTOR",
          "target": "ESR1",
          "interactionType": "phosphorylates",
          "color": "#00ff00",
          "lty": 1
        }
      },
      {
        "data": {
          "source": "AKT1",
          "target": "AKT1S1",
          "interactionType": "phosphorylates",
          "color": "#00ff00",
          "lty": 1
        }
      },
      {
        "data": {
          "source": "MAPK1",
          "target": "ESR1",
          "interactionType": "phosphorylates",
          "color": "#00ff00",
          "lty": 1
        }
      },
      {
        "data": {
          "source": "ESR1",
          "target": "MAPK1",
          "interactionType": "phosphorylates",
          "color": "#00ff00",
          "lty": 1
        }
      },
      {
        "data": {
          "source": "MAPK1",
          "target": "BAD",
          "interactionType": "phosphorylates",
          "color": "#00ff00",
          "lty": 1
        }
      },
      {
        "data": {
          "source": "AKT1",
          "target": "GSK3A",
          "interactionType": "phosphorylates",
          "color": "#00ff00",
          "lty": 1
        }
      },
      {
        "data": {
          "source": "MAPK1",
          "target": "GSK3B",
          "interactionType": "phosphorylates",
          "color": "#00ff00",
          "lty": 1
        }
      },
      {
        "data": {
          "source": "MTOR",
          "target": "AKT1S1",
          "interactionType": "phosphorylates",
          "color": "#00ff00",
          "lty": 1
        }
      }
    ]
  }
}
